videosdk/plugins/sarvamai/__init__.py
videosdk/plugins/sarvamai/llm.py
videosdk/plugins/sarvamai/stt.py
videosdk/plugins/sarvamai/tts.py
videosdk/plugins/sarvamai/version.py
videosdk_plugins_sarvamai-0.0.58.dist-info/METADATA
videosdk_plugins_sarvamai-0.0.58.dist-info/WHEEL
videosdk_plugins_sarvamai-0.0.58.dist-info/RECORD
