Metadata-Version: 2.4
Name: videosdk-plugins-sarvamai
Version: 0.0.58
Summary: VideoSDK Agent Framework plugin for SarvamAI
Author: videosdk
License-Expression: Apache-2.0
Keywords: ai,audio,sarvamai,video,videosdk
Classifier: Development Status :: 4 - Beta
Classifier: Intended Audience :: Developers
Classifier: Topic :: Communications :: Conferencing
Classifier: Topic :: Multimedia :: Sound/Audio
Classifier: Topic :: Multimedia :: Video
Classifier: Topic :: Scientific/Engineering :: Artificial Intelligence
Requires-Python: >=3.12
Requires-Dist: sarvamai
Requires-Dist: videosdk-agents>=0.0.58
